places_intel/__init__.py
places_intel/main.py
places_intel/outscraper_reviews.py
places_intel-0.2.3.dist-info/LICENSE
places_intel-0.2.3.dist-info/METADATA
places_intel-0.2.3.dist-info/WHEEL
places_intel-0.2.3.dist-info/top_level.txt
places_intel-0.2.3.dist-info/RECORD
