Metadata-Version: 2.1
Name: places-intel
Version: 0.2.3
Summary: A library for fetching and processing place data with polygons using Outscraper and Overpass APIs.
Home-page: UNKNOWN
Author: Blake Jennings
Author-email: blake@workerbeetech.com
License: MIT
Platform: UNKNOWN
Classifier: Programming Language :: Python :: 3
Classifier: License :: OSI Approved :: MIT License
Classifier: Operating System :: OS Independent
Requires-Python: >=3.6
License-File: LICENSE
Requires-Dist: outscraper
Requires-Dist: requests
Requires-Dist: overpy
Requires-Dist: pyspark
Requires-Dist: pandas
Requires-Dist: spark
